pincode_generator_or_validator/__init__.py
pincode_generator_or_validator-0.0.1.dist-info/LICENSE.txt
pincode_generator_or_validator-0.0.1.dist-info/METADATA
pincode_generator_or_validator-0.0.1.dist-info/WHEEL
pincode_generator_or_validator-0.0.1.dist-info/top_level.txt
pincode_generator_or_validator-0.0.1.dist-info/RECORD
