Metadata-Version: 2.1
Name: pincode_generator_or_validator
Version: 0.0.1
Summary: Pin Generator Package to generate Indian valid pin codes and also it can validate the Indian pin codes
Author: Soumya Roy
Author-email: roysoumya321@gmail.com
Classifier: Programming Language :: Python :: 3
Classifier: License :: OSI Approved :: MIT License
Classifier: Operating System :: OS Independent
Requires-Python: >=3.6
License-File: LICENSE.txt
